listmonk/__init__.py
listmonk/urls.py
listmonk/errors/__init__.py
listmonk/impl/__init__.py
listmonk/models/__init__.py
listmonk-0.3.9.dist-info/METADATA
listmonk-0.3.9.dist-info/WHEEL
listmonk-0.3.9.dist-info/licenses/LICENSE
listmonk-0.3.9.dist-info/RECORD
