Metadata-Version: 2.4
Name: listmonk
Version: 0.3.9
Summary: Listmonk Email API Client for Python
Project-URL: Homepage, https://github.com/mikeckennedy/listmonk
Project-URL: Tracker, https://github.com/mikeckennedy/listmonk/issues
Project-URL: Source, https://github.com/mikeckennedy/listmonk
Author-email: Michael Kennedy <michael@talkpython.fm>
License-Expression: MIT
License-File: LICENSE
Keywords: api-client,email,marketing,newsletters
Classifier: Development Status :: 5 - Production/Stable
Classifier: License :: OSI Approved :: MIT License
Classifier: Programming Language :: Python
Classifier: Programming Language :: Python :: 3
Classifier: Programming Language :: Python :: 3.10
Classifier: Programming Language :: Python :: 3.11
Classifier: Programming Language :: Python :: 3.12
Classifier: Programming Language :: Python :: 3.13
Classifier: Programming Language :: Python :: 3.14
Requires-Python: >=3.10
Requires-Dist: httpx
Requires-Dist: pydantic
Requires-Dist: strenum
